mysqltokenparser/MySqlLexer.py
mysqltokenparser/MySqlParser.py
mysqltokenparser/MySqlParserListener.py
mysqltokenparser/__init__.py
mysqltokenparser/constant.py
mysqltokenparser/mysqltokenparser.py
mysqltokenparser/utils.py
mysqltokenparser/sqltypemixins/__init__.py
mysqltokenparser/sqltypemixins/altertable.py
mysqltokenparser/sqltypemixins/createtable.py
mysqltokenparser/sqltypemixins/delete.py
mysqltokenparser/sqltypemixins/insert.py
mysqltokenparser/sqltypemixins/select.py
mysqltokenparser/sqltypemixins/update.py
mysqltokenparser-2.2.0.dist-info/AUTHORS.rst
mysqltokenparser-2.2.0.dist-info/LICENSE
mysqltokenparser-2.2.0.dist-info/METADATA
mysqltokenparser-2.2.0.dist-info/WHEEL
mysqltokenparser-2.2.0.dist-info/top_level.txt
mysqltokenparser-2.2.0.dist-info/RECORD
