Metadata-Version: 2.1
Name: mysqltokenparser
Version: 2.2.0
Summary: Get the mysql's tokens by the tool.
Home-page: https://github.com/LoveXiaoLiu/mysqltokenparser
Author: gra55
Author-email: shuai.grass@gmail.com
License: MIT license
Keywords: mysqltokenparser
Platform: UNKNOWN
Classifier: Development Status :: 2 - Pre-Alpha
Classifier: Intended Audience :: Developers
Classifier: License :: OSI Approved :: MIT License
Classifier: Natural Language :: English
Classifier: Programming Language :: Python :: 2
Classifier: Programming Language :: Python :: 2.7
Requires-Dist: antlr4-python2-runtime (==4.7.2)
